fakeish/__init__.py
fakeish/factory.py
fakeish/proxy.py
fakeish/objects/__init__.py
fakeish/objects/_samples/email_domains.yml
fakeish/objects/_samples/first_female.yml
fakeish/objects/_samples/first_male.yml
fakeish/objects/_samples/last.yml
fakeish/objects/email/__init__.py
fakeish/objects/name/__init__.py
fakeish/objects/ssn/__init__.py
fakeish/objects/string/__init__.py
fakeish/unique/__init__.py
fakeish/unique/email/__init__.py
fakeish/unique/name/__init__.py
fakeish/unique/ssn/__init__.py
fakeish/utils/__init__.py
fakeish/utils/loading.py
fakeish/utils/samples.py
fakeish-0.3.0.dist-info/LICENSE
fakeish-0.3.0.dist-info/METADATA
fakeish-0.3.0.dist-info/WHEEL
fakeish-0.3.0.dist-info/top_level.txt
fakeish-0.3.0.dist-info/RECORD
