Metadata-Version: 2.1
Name: fakeish
Version: 0.3.0
Summary: Faker but fast and dumb instead of slow and smart
Home-page: https://github.com/bengetch/fakeish
Author: bengetch
Author-email: bengetch@gmail.com
License: MIT
Platform: UNKNOWN
Requires-Python: >=3.5
License-File: LICENSE
Requires-Dist: pyyaml
